{
  "cli": {
    "version": ">= 16.27.0",
    "appVersionSource": "remote"
  },
  "build": {
    "development": {
      "developmentClient": true,
      "distribution": "internal",
      "env": {
        "EXPO_PUBLIC_GOOGLE_PLACES": ""
      },
      "channel": "development",
      "android": {
        "buildType": "apk"
      }
    },
    "preview": {
      "distribution": "internal",
      "channel": "preview",
      "android": {
        "gradleCommand": ":app:assembleRelease"
      }
    },
    "production": {
      "autoIncrement": true,
      "channel": "production"
    }
  },
  "submit": {
    "production": {}
  }
}
